pdf2imgCrop/__init__.py
pdf2imgCrop/__main__.py
pdf2imgCrop/core.py
pdf2imgcrop-0.1.0.dist-info/METADATA
pdf2imgcrop-0.1.0.dist-info/WHEEL
pdf2imgcrop-0.1.0.dist-info/entry_points.txt
pdf2imgcrop-0.1.0.dist-info/licenses/LICENSE.txt
pdf2imgcrop-0.1.0.dist-info/RECORD
