Metadata-Version: 2.4
Name: pdf2imgCrop
Version: 0.1.0
Summary: 将PDF文件转换为图片并自动裁剪空白边距
Author-email: Your Name <your.email@example.com>
License-File: LICENSE.txt
Requires-Python: >=3.8
Requires-Dist: pillow>=10.0.0
Requires-Dist: pymupdf>=1.23.0
Requires-Dist: tqdm>=4.65.0
